gmfind/__init__.py
gmfind/__main__.py
gmfind/blocklist_checker.py
gmfind/buy_game.py
gmfind/check_balance.py
gmfind/cli.py
gmfind/config.py
gmfind/game_check.py
gmfind/inventory.py
gmfind/inventory_private.py
gmfind/paths.py
gmfind/playwright_utils.py
gmfind/recommend_metacritic.py
gmfind/setup.py
gmfind/steam_auth.py
gmfind/deals/__init__.py
gmfind/deals/deals_aggregator.py
gmfind/deals/steam_specials.py
gmfind/recommendations/__init__.py
gmfind/recommendations/metacritic.py
gmfind/recommendations/protondb.py
gmfind/recommendations/steam_deck.py
gmfind/reports/__init__.py
gmfind/reports/markdown_generator.py
gmfind-0.1.14.dist-info/METADATA
gmfind-0.1.14.dist-info/WHEEL
gmfind-0.1.14.dist-info/entry_points.txt
gmfind-0.1.14.dist-info/licenses/LICENSE
gmfind-0.1.14.dist-info/RECORD
