Metadata-Version: 2.4
Name: gmfind
Version: 0.1.14
Summary: Steam automation CLI - find games, check deals, purchase, and manage your Steam library
Project-URL: Homepage, https://github.com/automoto/gmfind
Project-URL: Repository, https://github.com/automoto/gmfind
Project-URL: Issues, https://github.com/automoto/gmfind/issues
Author: gmfind contributors
License-Expression: MIT
License-File: LICENSE
Keywords: automation,cli,deals,gaming,playwright,steam
Classifier: Development Status :: 4 - Beta
Classifier: Environment :: Console
Classifier: Intended Audience :: End Users/Desktop
Classifier: License :: OSI Approved :: MIT License
Classifier: Operating System :: OS Independent
Classifier: Programming Language :: Python :: 3
Classifier: Programming Language :: Python :: 3.10
Classifier: Programming Language :: Python :: 3.11
Classifier: Programming Language :: Python :: 3.12
Classifier: Programming Language :: Python :: 3.13
Classifier: Topic :: Games/Entertainment
Requires-Python: >=3.10
Requires-Dist: beautifulsoup4>=4.12.0
Requires-Dist: msgspec>=0.18.0
Requires-Dist: platformdirs>=4.0.0
Requires-Dist: playwright>=1.40.0
Requires-Dist: pyyaml>=6.0
Requires-Dist: requests>=2.31.0
Provides-Extra: dev
Requires-Dist: mypy>=1.7.0; extra == 'dev'
Requires-Dist: pytest>=7.0.0; extra == 'dev'
Requires-Dist: ruff>=0.1.0; extra == 'dev'
Requires-Dist: types-pyyaml; extra == 'dev'
Requires-Dist: types-requests; extra == 'dev'
